ultan/__init__.py
ultan/cli.py
ultan/compat.py
ultan/get_doc.py
ultan/name_index.py
ultan/version.py
ultan/strategies/__init__.py
ultan/strategies/ast_walker.py
ultan/strategies/strategy.py
ultan/strategies/sys_modules_scanner.py
ultan-2.1.0.dist-info/METADATA
ultan-2.1.0.dist-info/RECORD
ultan-2.1.0.dist-info/WHEEL
ultan-2.1.0.dist-info/entry_points.txt
ultan-2.1.0.dist-info/top_level.txt
