Metadata-Version: 2.1
Name: ultan
Version: 2.1.0
Summary: Python name and documentation server
Home-page: https://github.com/sixty-north/ultan
Author: Sixty North AS
Author-email: austin@sixty-north.com
License: MIT
Platform: any
Classifier: Development Status :: 3 - Alpha
Classifier: Operating System :: OS Independent
Classifier: Programming Language :: Python
Classifier: Programming Language :: Python :: 3.4
Classifier: Programming Language :: Python :: 3.5
Classifier: Programming Language :: Python :: 3.6
Provides-Extra: test
Requires-Dist: docopt-subcommands
Provides-Extra: test
Requires-Dist: hypothesis; extra == 'test'
Requires-Dist: pytest; extra == 'test'
Requires-Dist: tox; extra == 'test'
